{"cameraMode":{"drawMode":0,"name":"Shaded","section":"Shading Mode"},"sceneLighting":false,"audioPlay":false,"sceneViewState":{"m_AlwaysRefresh":false,"showFog":true,"showSkybox":false,"showFlares":true,"showImageEffects":true,"showParticleSystems":true,"showVisualEffectGraphs":true,"m_FxEnabled":true},"in2DMode":false,"pivot":{"x":0.0,"y":1.3109588623046876,"z":0.0031295716762542726},"rotation":{"x":0.03898800536990166,"y":0.004796385299414396,"z":-0.00018714027828536928,"w":0.9992287755012512},"size":1.547118902206421,"orthographic":false}